{
"meta":{"test_sets":[],"test_metrics":[],"learn_metrics":[{"best_value":"Min","name":"RMSE"}],"launch_mode":"Train","parameters":"","iteration_count":100,"learn_sets":["learn"],"name":"experiment"},
"iterations":[
{"learn":[14.005006],"iteration":0,"passed_time":0.0008243101826,"remaining_time":0.08160670808},
{"learn":[13.14441192],"iteration":1,"passed_time":0.001586791648,"remaining_time":0.07775279074},
{"learn":[12.34258257],"iteration":2,"passed_time":0.002282871764,"remaining_time":0.0738128537},
{"learn":[11.64527793],"iteration":3,"passed_time":0.002841896914,"remaining_time":0.06820552593},
{"learn":[11.02766183],"iteration":4,"passed_time":0.003425052006,"remaining_time":0.06507598811},
{"learn":[10.43485794],"iteration":5,"passed_time":0.004013411938,"remaining_time":0.06287678703},
{"learn":[9.890641275],"iteration":6,"passed_time":0.004608185291,"remaining_time":0.06122303315},
{"learn":[9.492161212],"iteration":7,"passed_time":0.005132396356,"remaining_time":0.05902255809},
{"learn":[9.105082953],"iteration":8,"passed_time":0.005710886067,"remaining_time":0.05774340356},
{"learn":[8.674157135],"iteration":9,"passed_time":0.006244219207,"remaining_time":0.05619797287},
{"learn":[8.341743544],"iteration":10,"passed_time":0.006850687953,"remaining_time":0.05542829344},
{"learn":[8.049372916],"iteration":11,"passed_time":0.007439694291,"remaining_time":0.05455775814},
{"learn":[7.757318612],"iteration":12,"passed_time":0.0080147802,"remaining_time":0.05363737519},
{"learn":[7.522206899],"iteration":13,"passed_time":0.008644888642,"remaining_time":0.05310431595},
{"learn":[7.297756655],"iteration":14,"passed_time":0.009370135078,"remaining_time":0.05309743211},
{"learn":[7.088359431],"iteration":15,"passed_time":0.009906969029,"remaining_time":0.0520115874},
{"learn":[6.882113791],"iteration":16,"passed_time":0.01046959531,"remaining_time":0.05111625945},
{"learn":[6.704728832],"iteration":17,"passed_time":0.01103761997,"remaining_time":0.05028249099},
{"learn":[6.563881962],"iteration":18,"passed_time":0.01159711313,"remaining_time":0.04944032439},
{"learn":[6.418790279],"iteration":19,"passed_time":0.01218189843,"remaining_time":0.04872759372},
{"learn":[6.315756953],"iteration":20,"passed_time":0.0127465368,"remaining_time":0.04795125749},
{"learn":[6.210157751],"iteration":21,"passed_time":0.01332775646,"remaining_time":0.04725295473},
{"learn":[6.115058449],"iteration":22,"passed_time":0.0139255224,"remaining_time":0.04662022716},
{"learn":[6.014819884],"iteration":23,"passed_time":0.01442288729,"remaining_time":0.04567247643},
{"learn":[5.93117229],"iteration":24,"passed_time":0.01495088262,"remaining_time":0.04485264786},
{"learn":[5.844857622],"iteration":25,"passed_time":0.01549265783,"remaining_time":0.04409448768},
{"learn":[5.771145213],"iteration":26,"passed_time":0.01607672054,"remaining_time":0.04346668888},
{"learn":[5.704018229],"iteration":27,"passed_time":0.0166129521,"remaining_time":0.04271901968},
{"learn":[5.665806474],"iteration":28,"passed_time":0.01721640223,"remaining_time":0.04215050202},
{"learn":[5.616500369],"iteration":29,"passed_time":0.01778206179,"remaining_time":0.04149147752},
{"learn":[5.558023666],"iteration":30,"passed_time":0.01843137453,"remaining_time":0.04102467234},
{"learn":[5.510080976],"iteration":31,"passed_time":0.01907466141,"remaining_time":0.04053365549},
{"learn":[5.468747792],"iteration":32,"passed_time":0.01971711496,"remaining_time":0.04003171826},
{"learn":[5.429275534],"iteration":33,"passed_time":0.02037263811,"remaining_time":0.03954688575},
{"learn":[5.402117324],"iteration":34,"passed_time":0.0210252283,"remaining_time":0.03904685257},
{"learn":[5.367635151],"iteration":35,"passed_time":0.0216158005,"remaining_time":0.03842808977},
{"learn":[5.345181232],"iteration":36,"passed_time":0.02223901663,"remaining_time":0.03786643372},
{"learn":[5.319151269],"iteration":37,"passed_time":0.02287291075,"remaining_time":0.03731895965},
{"learn":[5.296134146],"iteration":38,"passed_time":0.0234775548,"remaining_time":0.03672130366},
{"learn":[5.269629003],"iteration":39,"passed_time":0.02403477465,"remaining_time":0.03605216198},
{"learn":[5.251147059],"iteration":40,"passed_time":0.02460933104,"remaining_time":0.03541342759},
{"learn":[5.248003302],"iteration":41,"passed_time":0.02490744173,"remaining_time":0.03439599096},
{"learn":[5.232376509],"iteration":42,"passed_time":0.02551161493,"remaining_time":0.03381772212},
{"learn":[5.213524255],"iteration":43,"passed_time":0.02610697932,"remaining_time":0.03322706459},
{"learn":[5.189691584],"iteration":44,"passed_time":0.02670156528,"remaining_time":0.03263524646},
{"learn":[5.166052198],"iteration":45,"passed_time":0.02732367127,"remaining_time":0.0320756141},
{"learn":[5.140406659],"iteration":46,"passed_time":0.02798191916,"remaining_time":0.03155407905},
{"learn":[5.118929684],"iteration":47,"passed_time":0.02854678988,"remaining_time":0.03092568904},
{"learn":[5.108792602],"iteration":48,"passed_time":0.02911802386,"remaining_time":0.03030651463},
{"learn":[5.098141225],"iteration":49,"passed_time":0.0296447524,"remaining_time":0.0296447524},
{"learn":[5.085926393],"iteration":50,"passed_time":0.03023155452,"remaining_time":0.02904600337},
{"learn":[5.067816804],"iteration":51,"passed_time":0.03096344578,"remaining_time":0.02858164226},
{"learn":[5.049834901],"iteration":52,"passed_time":0.03154815158,"remaining_time":0.02797666272},
{"learn":[5.03838627],"iteration":53,"passed_time":0.03213329321,"remaining_time":0.02737280533},
{"learn":[5.033534248],"iteration":54,"passed_time":0.03251184303,"remaining_time":0.02660059884},
{"learn":[5.023726885],"iteration":55,"passed_time":0.0331731649,"remaining_time":0.02606462957},
{"learn":[5.01290392],"iteration":56,"passed_time":0.03380612444,"remaining_time":0.0255028658},
{"learn":[5.005569127],"iteration":57,"passed_time":0.03438235788,"remaining_time":0.0248975695},
{"learn":[4.989969032],"iteration":58,"passed_time":0.03489355992,"remaining_time":0.02424806706},
{"learn":[4.976762446],"iteration":59,"passed_time":0.03543019938,"remaining_time":0.02362013292},
{"learn":[4.967222715],"iteration":60,"passed_time":0.03593404489,"remaining_time":0.02297422542},
{"learn":[4.954407599],"iteration":61,"passed_time":0.0364599827,"remaining_time":0.02234644101},
{"learn":[4.942125056],"iteration":62,"passed_time":0.03702185137,"remaining_time":0.02174299208},
{"learn":[4.930230716],"iteration":63,"passed_time":0.03769188221,"remaining_time":0.02120168374},
{"learn":[4.921695642],"iteration":64,"passed_time":0.03834834089,"remaining_time":0.02064910663},
{"learn":[4.906405625],"iteration":65,"passed_time":0.03888609571,"remaining_time":0.02003223112},
{"learn":[4.894330248],"iteration":66,"passed_time":0.03945371531,"remaining_time":0.01943242694},
{"learn":[4.88211557],"iteration":67,"passed_time":0.04005584897,"remaining_time":0.01884981128},
{"learn":[4.877946398],"iteration":68,"passed_time":0.04069540553,"remaining_time":0.01828344307},
{"learn":[4.863182126],"iteration":69,"passed_time":0.0413262025,"remaining_time":0.01771122964},
{"learn":[4.84646533],"iteration":70,"passed_time":0.04185213794,"remaining_time":0.01709453521},
{"learn":[4.838014752],"iteration":71,"passed_time":0.04245734653,"remaining_time":0.01651119032},
{"learn":[4.82981137],"iteration":72,"passed_time":0.04308437058,"remaining_time":0.01593531515},
{"learn":[4.817094767],"iteration":73,"passed_time":0.04363288904,"remaining_time":0.01533047453},
{"learn":[4.808314151],"iteration":74,"passed_time":0.04418090732,"remaining_time":0.01472696911},
{"learn":[4.796235023],"iteration":75,"passed_time":0.04484218045,"remaining_time":0.01416068856},
{"learn":[4.784434534],"iteration":76,"passed_time":0.04547860105,"remaining_time":0.0135845172},
{"learn":[4.774402487],"iteration":77,"passed_time":0.04600404861,"remaining_time":0.01297550089},
{"learn":[4.76731896],"iteration":78,"passed_time":0.04662847995,"remaining_time":0.01239491239},
{"learn":[4.75934113],"iteration":79,"passed_time":0.04726953658,"remaining_time":0.01181738415},
{"learn":[4.754106378],"iteration":80,"passed_time":0.04782484609,"remaining_time":0.01121817377},
{"learn":[4.744002932],"iteration":81,"passed_time":0.0483999831,"remaining_time":0.01062438653},
{"learn":[4.731700554],"iteration":82,"passed_time":0.04898516448,"remaining_time":0.01003310598},
{"learn":[4.723284153],"iteration":83,"passed_time":0.04956412835,"remaining_time":0.009440786352},
{"learn":[4.712232782],"iteration":84,"passed_time":0.05013386367,"remaining_time":0.008847152412},
{"learn":[4.703046867],"iteration":85,"passed_time":0.0506597499,"remaining_time":0.00824693603},
{"learn":[4.698601855],"iteration":86,"passed_time":0.05122140326,"remaining_time":0.0076537729},
{"learn":[4.692429407],"iteration":87,"passed_time":0.05179932322,"remaining_time":0.007063544076},
{"learn":[4.675027364],"iteration":88,"passed_time":0.05233348685,"remaining_time":0.006468183768},
{"learn":[4.662368584],"iteration":89,"passed_time":0.05290273997,"remaining_time":0.005878082218},
{"learn":[4.646206172],"iteration":90,"passed_time":0.05346594025,"remaining_time":0.005287840245},
{"learn":[4.641245848],"iteration":91,"passed_time":0.05398563358,"remaining_time":0.00469440292},
{"learn":[4.633900435],"iteration":92,"passed_time":0.05454660741,"remaining_time":0.004105658622},
{"learn":[4.624738236],"iteration":93,"passed_time":0.0551825387,"remaining_time":0.003522289704},
{"learn":[4.612798287],"iteration":94,"passed_time":0.05578250223,"remaining_time":0.00293592117},
{"learn":[4.605222001],"iteration":95,"passed_time":0.05635136873,"remaining_time":0.002347973697},
{"learn":[4.601725912],"iteration":96,"passed_time":0.05689109116,"remaining_time":0.001759518283},
{"learn":[4.59722371],"iteration":97,"passed_time":0.05744379942,"remaining_time":0.001172322437},
{"learn":[4.580235665],"iteration":98,"passed_time":0.05796728458,"remaining_time":0.0005855281271},
{"learn":[4.57591791],"iteration":99,"passed_time":0.05847168186,"remaining_time":0}
]}